{
  "name": "Living Bigby's Hand",
  "size": "L",
  "type": "construct",
  "alignment": "U",
  "armor_class": 20,
  "hit_points": {
    "average": 52,
    "formula": "5d10 + 25"
  },
  "speed": {
    "walk": 0,
    "fly": 60,
    "canHover": 1
  },
  "abilities": {
    "str": 26,
    "dex": 10,
    "con": 20,
    "int": 1,
    "wis": 10,
    "cha": 1
  },
  "challenge_rating": 4.0,
  "source": "IDRotF",
  "saving_throws": {
    "dex": "+2",
    "wis": "+2"
  },
  "skills": {
    "perception": "+2",
    "stealth": "+2"
  },
  "damage_vulnerabilities": [],
  "damage_resistances": [],
  "damage_immunities": [
    "poison"
  ],
  "condition_immunities": [
    "blinded",
    "charmed",
    "deafened",
    "exhaustion",
    "frightened",
    "paralyzed",
    "petrified",
    "poisoned",
    "unconscious"
  ],
  "senses": [
    "darkvision 60 ft."
  ],
  "languages": [],
  "trait": [
    {
      "name": "Magic Resistance",
      "entries": [
        "The living spell has advantage on saving throws against spells and other magical effects."
      ]
    },
    {
      "name": "Unusual Nature",
      "entries": [
        "The living spell doesn't require air, food, drink, or sleep."
      ]
    }
  ],
  "action": [
    {
      "name": "Force Fist",
      "entries": [
        "{@atk ms} {@hit 10} to hit, reach 5 ft., one target. {@h}26 ({@damage 4d8 + 8}) force damage. If the target is a Large or smaller creature, the living spell can move it up to 5 feet and move with it, without provoking opportunity attacks."
      ]
    },
    {
      "name": "Grasping Hand",
      "entries": [
        "The living spell attempts to grab a Huge or smaller creature within 5 feet of it. The target must succeed on a {@dc 15} Dexterity saving throw or be {@condition grappled} (escape {@dc 15}). Until the grapple ends, the target takes 15 ({@damage 2d6 + 8}) bludgeoning damage at the start of each of its turns. The living spell can grapple only one creature at a time and can't use Force Fist until the grapple ends."
      ]
    }
  ],
  "reaction": [],
  "legendary": [],
  "spellcasting": [],
  "_5etools": {
    "page": 298,
    "otherSources": [],
    "environment": [],
    "soundClip": null,
    "isNpc": false
  }
}