{
  "name": "Reduced-Threat Behir",
  "size": "L",
  "type": "monstrosity",
  "alignment": "N",
  "armor_class": 17,
  "hit_points": {
    "average": 84,
    "formula": "floor((16d12 + 64) ÷ 2)"
  },
  "speed": {
    "walk": 50,
    "climb": 40
  },
  "abilities": {
    "str": 23,
    "dex": 16,
    "con": 18,
    "int": 7,
    "wis": 14,
    "cha": 12
  },
  "challenge_rating": 11.0,
  "source": "TftYP",
  "saving_throws": {},
  "skills": {
    "perception": "+4",
    "stealth": "+5"
  },
  "damage_vulnerabilities": [],
  "damage_resistances": [],
  "damage_immunities": [
    "lightning"
  ],
  "condition_immunities": [],
  "senses": [
    "darkvision 90 ft."
  ],
  "languages": [
    "Draconic"
  ],
  "trait": [
    {
      "name": "Reduced Threat",
      "entries": [
        "A reduced-threat monster takes a −2 penalty on attack rolls (included in the stat block), ability checks (included in the stat block for skill proficiencies), saving throws (included in the stat block for saving throw proficiencies), and saving throw DCs (included in the stat block)."
      ]
    }
  ],
  "action": [
    {
      "name": "Multiattack",
      "entries": [
        "The behir makes two attacks: one with its bite and one to constrict."
      ]
    },
    {
      "name": "Bite",
      "entries": [
        "{@atk mw} {@hit 8} to hit, reach 10 ft., one target. {@h}22 ({@damage 3d10 + 6}) piercing damage."
      ]
    },
    {
      "name": "Lightning Breath {@recharge 5}",
      "entries": [
        "The behir exhales a line of lightning that is 20 feet long and 5 feet wide. Each creature in that line must make a {@dc 14} Dexterity saving throw, taking 66 ({@damage 12d10}) lightning damage on a failed save, or half as much damage on a successful one."
      ]
    }
  ],
  "reaction": [],
  "legendary": [],
  "spellcasting": [],
  "_5etools": {
    "page": 113,
    "otherSources": [],
    "environment": [],
    "soundClip": null,
    "isNpc": false
  }
}