<?xml version="1.0"?>
<Ideal createdAt="1999-03-26" createdBy="graebe" id="Cyclic_4">
<!-- $Id: Cyclic_4.xml,v 1.1 2006/03/04 21:18:36 graebe Exp $ -->
  <hasIsolatedPrimeDimensions>1 1</hasIsolatedPrimeDimensions>
  <theBaseDomain>Z</theBaseDomain>
  <theDimension>1</theDimension>
  <theGenerators>
    <OWL xref="Cyclic_4" class="IntegerPolynomialSystem"/>
  </theGenerators>
  <theVariableList>w,x,y,z</theVariableList>
  <Comment/>
  <ChangeLog>
    <changed at="2006-03-03" by="graebe">compiled from XMLData INTPS/Cyclic_4</changed>
  </ChangeLog>
</Ideal>
