{
  "name": "Githzerai Monk",
  "size": "M",
  "type": {
    "type": "aberration",
    "tags": [
      "gith"
    ]
  },
  "alignment": "L",
  "armor_class": 14,
  "hit_points": {
    "average": 38,
    "formula": "7d8 + 7"
  },
  "speed": {
    "walk": 40
  },
  "abilities": {
    "str": 12,
    "dex": 15,
    "con": 12,
    "int": 13,
    "wis": 14,
    "cha": 10
  },
  "challenge_rating": 2.0,
  "source": "XMM",
  "saving_throws": {
    "str": "+3",
    "dex": "+4",
    "int": "+3",
    "wis": "+4"
  },
  "skills": {
    "insight": "+4",
    "perception": "+4"
  },
  "damage_vulnerabilities": [],
  "damage_resistances": [],
  "damage_immunities": [],
  "condition_immunities": [],
  "senses": [],
  "languages": [
    "Common",
    "Gith"
  ],
  "trait": [],
  "action": [
    {
      "name": "Multiattack",
      "entries": [
        "The githzerai makes two Psi Strike attacks."
      ]
    },
    {
      "name": "Psi Strike",
      "entries": [
        "{@atkr m} {@hit 4}, reach 5 ft. {@h}6 ({@damage 1d8 + 2}) Bludgeoning damage plus 9 ({@damage 2d8}) Psychic damage."
      ]
    }
  ],
  "reaction": [],
  "legendary": [],
  "spellcasting": [
    {
      "name": "Spellcasting",
      "type": "spellcasting",
      "headerEntries": [
        "The githzerai casts one of the following spells, requiring no spell components and using Wisdom as the spellcasting ability:"
      ],
      "will": [
        "{@spell Mage Hand|XPHB} (the hand is Invisible)"
      ],
      "daily": {
        "1": [
          "{@spell See Invisibility|XPHB}"
        ]
      },
      "ability": "wis",
      "displayAs": "action"
    },
    {
      "name": "Psi-Powered Leap (2/Day)",
      "type": "spellcasting",
      "headerEntries": [
        "The githzerai casts {@spell Jump|XPHB}, requiring no spell components and using the same spellcasting ability as Spellcasting."
      ],
      "daily": {
        "2": [
          "{@spell Jump|XPHB}"
        ]
      },
      "ability": "wis",
      "displayAs": "bonus",
      "hidden": [
        "daily"
      ]
    },
    {
      "name": "Psionic Defense (2/Day)",
      "type": "spellcasting",
      "headerEntries": [
        "The githzerai casts {@spell Feather Fall|XPHB} or {@spell Shield|XPHB} in response to the spell's trigger, requiring no spell components and using the same spellcasting ability as Spellcasting."
      ],
      "daily": {
        "2": [
          "{@spell Feather Fall|XPHB}",
          "{@spell Shield|XPHB}"
        ]
      },
      "ability": "wis",
      "displayAs": "reaction",
      "hidden": [
        "daily"
      ]
    }
  ],
  "_5etools": {
    "page": 136,
    "otherSources": [],
    "environment": [
      "planar, limbo"
    ],
    "soundClip": {
      "type": "internal",
      "path": "bestiary/githzerai-monk.mp3"
    },
    "isNpc": false
  }
}