{
  "name": "Goblin Commoner",
  "size": "S",
  "type": {
    "type": "humanoid",
    "tags": [
      "goblinoid"
    ]
  },
  "alignment": "A",
  "armor_class": 10,
  "hit_points": {
    "average": 3,
    "formula": "1d6"
  },
  "speed": {
    "walk": 30
  },
  "abilities": {
    "str": 8,
    "dex": 10,
    "con": 10,
    "int": 10,
    "wis": 10,
    "cha": 10
  },
  "challenge_rating": 0.0,
  "source": "TftYP",
  "saving_throws": {},
  "skills": {},
  "damage_vulnerabilities": [],
  "damage_resistances": [],
  "damage_immunities": [],
  "condition_immunities": [],
  "senses": [
    "darkvision 60 ft."
  ],
  "languages": [
    "any one language (usually Common)",
    "Goblin"
  ],
  "trait": [
    {
      "name": "Nimble Escape",
      "entries": [
        "The goblin commoner can take the {@action Disengage} or {@action Hide} action as a bonus action on each of its turns."
      ]
    }
  ],
  "action": [
    {
      "name": "Club",
      "entries": [
        "{@atk mw} {@hit 1} to hit, reach 5 ft., one target. {@h}1 ({@damage 1d4 - 1}) bludgeoning damage."
      ]
    }
  ],
  "reaction": [],
  "legendary": [],
  "spellcasting": [],
  "_5etools": {
    "page": 24,
    "otherSources": [],
    "environment": [],
    "soundClip": null,
    "isNpc": false
  }
}