{
  "name": "Incarnation of Vibrance",
  "size": "H",
  "type": "fey",
  "alignment": "N",
  "armor_class": 14,
  "hit_points": {
    "average": 230,
    "formula": "20d12 + 100"
  },
  "speed": {
    "walk": 40
  },
  "abilities": {
    "str": 20,
    "dex": 17,
    "con": 20,
    "int": 10,
    "wis": 16,
    "cha": 21
  },
  "challenge_rating": 10.0,
  "source": "LFL",
  "saving_throws": {
    "con": "+9",
    "cha": "+9"
  },
  "skills": {},
  "damage_vulnerabilities": [],
  "damage_resistances": [
    "radiant"
  ],
  "damage_immunities": [],
  "condition_immunities": [
    "blinded",
    "charmed",
    "deafened",
    "frightened"
  ],
  "senses": [
    "Darkvision 60 ft."
  ],
  "languages": [
    "Sylvan; telepathy 120 ft."
  ],
  "trait": [
    {
      "name": "Magic Resistance",
      "entries": [
        "The incarnation has {@variantrule Advantage|XPHB} on saving throws against spells and other magical effects."
      ]
    }
  ],
  "action": [
    {
      "name": "Multiattack",
      "entries": [
        "The incarnation makes two Vine attacks and uses Radiant Blast. It can replace one vine attack with a use of Spellcasting to cast {@spell Blindness/Deafness|XPHB} if available."
      ]
    },
    {
      "name": "Vine",
      "entries": [
        "{@atkr m} {@hit 9}, reach 20 ft. {@h}18 ({@damage 3d8 + 5}) Bludgeoning damage. If the target is the incarnation's size or smaller, it has the {@condition Grappled|XPHB} condition (escape {@dc 15}) from one of two vines."
      ]
    },
    {
      "name": "Radiant Blast",
      "entries": [
        "{@actSave con} {@dc 17}, each creature of the incarnation's choice in a 20-foot {@variantrule Emanation [Area of Effect]|XPHB|Emanation} originating from the incarnation. {@actSaveFail} The creature takes 14 ({@damage 2d8 + 5}) Radiant damage. {@actSaveSuccess} Half damage."
      ]
    }
  ],
  "reaction": [],
  "legendary": [],
  "spellcasting": [
    {
      "name": "Spellcasting",
      "type": "spellcasting",
      "headerEntries": [
        "The incarnation casts one of the following spells, requiring no spell components and using Charisma as the spellcasting ability:"
      ],
      "will": [
        "{@spell Daylight|XPHB}",
        "{@spell Druidcraft|XPHB}",
        "{@spell Plant Growth|XPHB}"
      ],
      "daily": {
        "1": [
          "{@spell Blindness/Deafness|XPHB}"
        ]
      },
      "ability": "cha",
      "displayAs": "action"
    }
  ],
  "_5etools": {
    "page": null,
    "otherSources": [],
    "environment": [
      "planar, feywild"
    ],
    "soundClip": null,
    "isNpc": false
  }
}