{
  "name": "Mammoth",
  "size": "H",
  "type": "beast",
  "alignment": "U",
  "armor_class": 13,
  "hit_points": {
    "average": 126,
    "formula": "11d12 + 55"
  },
  "speed": {
    "walk": 50
  },
  "abilities": {
    "str": 24,
    "dex": 9,
    "con": 21,
    "int": 3,
    "wis": 11,
    "cha": 6
  },
  "challenge_rating": 6.0,
  "source": "XMM",
  "saving_throws": {
    "str": "+10",
    "con": "+8"
  },
  "skills": {},
  "damage_vulnerabilities": [],
  "damage_resistances": [],
  "damage_immunities": [],
  "condition_immunities": [],
  "senses": [],
  "languages": [],
  "trait": [],
  "action": [
    {
      "name": "Multiattack",
      "entries": [
        "The mammoth makes two Gore attacks."
      ]
    },
    {
      "name": "Gore",
      "entries": [
        "{@atkr m} {@hit 10}, reach 10 ft. {@h}18 ({@damage 2d10 + 7}) Piercing damage. If the target is a Huge or smaller creature and the mammoth moved 20+ feet straight toward it immediately before the hit, the target has the {@condition Prone|XPHB} condition."
      ]
    }
  ],
  "reaction": [],
  "legendary": [],
  "spellcasting": [],
  "_5etools": {
    "page": 365,
    "otherSources": [
      {
        "source": "DrDe"
      },
      {
        "source": "FRAiF"
      },
      {
        "source": "NF"
      }
    ],
    "environment": [
      "arctic"
    ],
    "soundClip": {
      "type": "internal",
      "path": "bestiary/mammoth.mp3"
    },
    "isNpc": false
  }
}