{
  "name": "Sentinel Marshal",
  "size": "S",
  "type": {
    "type": "humanoid",
    "tags": [
      "Human"
    ]
  },
  "alignment": "L",
  "armor_class": 16,
  "hit_points": {
    "average": 110,
    "formula": "20d8 + 20"
  },
  "speed": {
    "walk": 30
  },
  "abilities": {
    "str": 18,
    "dex": 19,
    "con": 12,
    "int": 11,
    "wis": 15,
    "cha": 10
  },
  "challenge_rating": 6.0,
  "source": "EFA",
  "saving_throws": {
    "dex": "+7",
    "con": "+4"
  },
  "skills": {
    "athletics": "+7",
    "insight": "+5",
    "perception": "+8"
  },
  "damage_vulnerabilities": [],
  "damage_resistances": [],
  "damage_immunities": [],
  "condition_immunities": [],
  "senses": [],
  "languages": [
    "Common plus two other languages"
  ],
  "trait": [],
  "action": [
    {
      "name": "Multiattack",
      "entries": [
        "The marshal makes three attacks, using Longsword or Pistol in any combination."
      ]
    },
    {
      "name": "Longsword",
      "entries": [
        "{@atkr m} {@hit 7}, reach 5 ft. {@h}13 ({@damage 2d8 + 4}) Slashing damage, and the target has {@variantrule Disadvantage|XPHB} on the next attack roll it makes before the start of the marshal's next turn."
      ]
    },
    {
      "name": "Pistol",
      "entries": [
        "{@atkr r} {@hit 7}, range 30/90 ft. {@h}15 ({@damage 2d10 + 4}) Piercing damage."
      ]
    }
  ],
  "reaction": [],
  "legendary": [],
  "spellcasting": [
    {
      "name": "Shield (3/Day)",
      "type": "spellcasting",
      "headerEntries": [
        "The marshal casts {@spell Shield|XPHB} in response to the spell's trigger, using Wisdom as the spellcasting ability."
      ],
      "daily": {
        "3": [
          "{@spell Shield|XPHB}"
        ]
      },
      "ability": "wis",
      "displayAs": "reaction",
      "hidden": [
        "daily"
      ]
    }
  ],
  "_5etools": {
    "page": 83,
    "otherSources": [],
    "environment": [],
    "soundClip": null,
    "isNpc": false
  }
}