{
  "name": "Internal Network Pentest",
  "description": "Standard Internal Network Penetration Testing Deliverables",
  "framework": "internal",
  "engagement_type": "network",
  "deliverables": [
    {
      "category": "reconnaissance",
      "title": "Network Discovery & Mapping",
      "description": "Identify live hosts, subnets, and network topology",
      "target_type": "count",
      "target_value": 20,
      "auto_validate": true,
      "validation_query": "SELECT COUNT(*) as count FROM hosts",
      "priority": "critical"
    },
    {
      "category": "enumeration",
      "title": "Service Enumeration",
      "description": "Enumerate services, versions, and potential attack surface",
      "target_type": "count",
      "target_value": 50,
      "auto_validate": true,
      "validation_query": "SELECT COUNT(*) as count FROM services",
      "priority": "critical"
    },
    {
      "category": "enumeration",
      "title": "Active Directory Enumeration",
      "description": "Enumerate AD users, groups, trusts, and policies",
      "target_type": "boolean",
      "target_value": 1,
      "auto_validate": true,
      "validation_query": "SELECT COUNT(*) as count FROM findings WHERE title LIKE '%Active Directory%' OR title LIKE '%LDAP%'",
      "priority": "critical"
    },
    {
      "category": "enumeration",
      "title": "SMB/NetBIOS Enumeration",
      "description": "Enumerate SMB shares, null sessions, and NetBIOS information",
      "target_type": "count",
      "target_value": 5,
      "auto_validate": true,
      "validation_query": "SELECT COUNT(*) as count FROM services WHERE port IN (139, 445)",
      "priority": "high"
    },
    {
      "category": "exploitation",
      "title": "Credential Harvesting",
      "description": "Capture and crack credentials through various techniques",
      "target_type": "count",
      "target_value": 5,
      "auto_validate": true,
      "validation_query": "SELECT COUNT(*) as count FROM credentials",
      "priority": "critical"
    },
    {
      "category": "exploitation",
      "title": "Vulnerability Exploitation",
      "description": "Exploit identified vulnerabilities to gain initial access",
      "target_type": "count",
      "target_value": 3,
      "auto_validate": true,
      "validation_query": "SELECT COUNT(*) as count FROM findings WHERE severity = 'critical'",
      "priority": "critical"
    },
    {
      "category": "post_exploitation",
      "title": "Lateral Movement",
      "description": "Move laterally through the network to reach high-value targets",
      "target_type": "boolean",
      "target_value": 1,
      "auto_validate": false,
      "priority": "critical"
    },
    {
      "category": "post_exploitation",
      "title": "Domain Compromise Assessment",
      "description": "Assess path to domain admin or equivalent privileges",
      "target_type": "boolean",
      "target_value": 1,
      "auto_validate": true,
      "validation_query": "SELECT COUNT(*) as count FROM credentials WHERE username LIKE '%admin%'",
      "priority": "critical"
    }
  ]
}
