{
    "octaves": {
        "oct1": {
            "name": "oct1",
            "ip": "134.94.1.250",
            "port": 11051,
            "calibration_db_path": "/p/project1/cqc/karnad1/home/Sandbox/Projects/northface-qua-libs",
            "RF_outputs": {
                "1": {
                    "id": 1,
                    "channel": "#/qubits/q3/resonator",
                    "LO_frequency": 7600000000,
                    "gain": -20,
                    "output_mode": "always_on"
                },
                "2": {
                    "id": 2,
                    "channel": "#/qubits/q4/xy",
                    "LO_frequency": 6100000000.0,
                    "output_mode": "always_on"
                },
                "3": {
                    "id": 3,
                    "channel": "#/qubits/q3/xy",
                    "LO_frequency": 6100000000.0,
                    "output_mode": "always_on"
                },
                "4": {
                    "id": 4,
                    "channel": "#/qubits/q2/xy",
                    "LO_frequency": 4900000000.0,
                    "output_mode": "always_on"
                },
                "5": {
                    "id": 5,
                    "channel": "#/qubits/q1/xy",
                    "LO_frequency": 4900000000.0,
                    "output_mode": "always_on"
                }
            },
            "RF_inputs": {
                "1": {
                    "id": 1,
                    "channel": "#/qubits/q3/resonator",
                    "LO_frequency": 7600000000
                },
                "2": {
                    "id": 2,
                    "LO_source": "external"
                }
            }
        },
        "oct2": {
            "name": "oct2",
            "ip": "134.94.1.250",
            "port": 11050,
            "calibration_db_path": "/p/project1/cqc/karnad1/home/Sandbox/Projects/northface-qua-libs",
            "RF_outputs": {
                "1": {
                    "id": 1,
                    "channel": "#/qubits/q4/resonator",
                    "LO_frequency": 8600000000,
                    "gain": -20,
                    "output_mode": "always_on"
                },
                "2": {
                    "id": 2,
                    "channel": "#/qubits/q0/xy",
                    "LO_frequency": 4900000000.0,
                    "output_mode": "always_on"
                },
                "3": {
                    "id": 3
                },
                "4": {
                    "id": 4
                },
                "5": {
                    "id": 5
                }
            },
            "RF_inputs": {
                "1": {
                    "id": 1,
                    "channel": "#/qubits/q4/resonator",
                    "LO_frequency": 8600000000
                },
                "2": {
                    "id": 2,
                    "LO_source": "external"
                }
            }
        }
    },
    "qubits": {
        "q0": {
            "id": "q0",
            "xy": {
                "operations": {
                    "x180_DragCosine": {
                        "length": 32,
                        "digital_marker": "ON",
                        "axis_angle": 0,
                        "amplitude": 0.11636290849317382,
                        "alpha": -0.1477090444870001,
                        "anharmonicity": "#/qubits/q0/anharmonicity",
                        "detuning": 150000.0,
                        "__class__": "quam.components.pulses.DragCosinePulse"
                    },
                    "x90_DragCosine": {
                        "length": "#../x180_DragCosine/length",
                        "digital_marker": "ON",
                        "axis_angle": 0,
                        "amplitude": 0.05818145424658691,
                        "alpha": "#../x180_DragCosine/alpha",
                        "anharmonicity": "#../x180_DragCosine/anharmonicity",
                        "detuning": -2350000.0,
                        "__class__": "quam.components.pulses.DragCosinePulse"
                    },
                    "-x90_DragCosine": {
                        "length": "#../x180_DragCosine/length",
                        "digital_marker": "ON",
                        "axis_angle": 3.141592653589793,
                        "amplitude": "#../x90_DragCosine/amplitude",
                        "alpha": "#../x90_DragCosine/alpha",
                        "anharmonicity": "#../x180_DragCosine/anharmonicity",
                        "detuning": "#../x90_DragCosine/detuning",
                        "__class__": "quam.components.pulses.DragCosinePulse"
                    },
                    "y180_DragCosine": {
                        "length": "#../x180_DragCosine/length",
                        "digital_marker": "ON",
                        "axis_angle": 1.5707963267948966,
                        "amplitude": "#../x180_DragCosine/amplitude",
                        "alpha": "#../x180_DragCosine/alpha",
                        "anharmonicity": "#../x180_DragCosine/anharmonicity",
                        "detuning": "#../x180_DragCosine/detuning",
                        "__class__": "quam.components.pulses.DragCosinePulse"
                    },
                    "y90_DragCosine": {
                        "length": "#../x90_DragCosine/length",
                        "digital_marker": "ON",
                        "axis_angle": 1.5707963267948966,
                        "amplitude": "#../x90_DragCosine/amplitude",
                        "alpha": "#../x90_DragCosine/alpha",
                        "anharmonicity": "#../x180_DragCosine/anharmonicity",
                        "detuning": "#../x90_DragCosine/detuning",
                        "__class__": "quam.components.pulses.DragCosinePulse"
                    },
                    "-y90_DragCosine": {
                        "length": "#../x180_DragCosine/length",
                        "digital_marker": "ON",
                        "axis_angle": -1.5707963267948966,
                        "amplitude": "#../x90_DragCosine/amplitude",
                        "alpha": "#../x90_DragCosine/alpha",
                        "anharmonicity": "#../x180_DragCosine/anharmonicity",
                        "detuning": "#../x90_DragCosine/detuning",
                        "__class__": "quam.components.pulses.DragCosinePulse"
                    },
                    "x180_Square": {
                        "length": 100,
                        "digital_marker": "ON",
                        "amplitude": 0.25,
                        "axis_angle": 0,
                        "__class__": "quam.components.pulses.SquarePulse"
                    },
                    "x90_Square": {
                        "length": "#../x180_Square/length",
                        "digital_marker": "ON",
                        "amplitude": 0.125,
                        "axis_angle": 0,
                        "__class__": "quam.components.pulses.SquarePulse"
                    },
                    "-x90_Square": {
                        "length": "#../x180_Square/length",
                        "digital_marker": "ON",
                        "amplitude": -0.125,
                        "axis_angle": 0,
                        "__class__": "quam.components.pulses.SquarePulse"
                    },
                    "y180_Square": {
                        "length": "#../x180_Square/length",
                        "digital_marker": "ON",
                        "amplitude": 0.25,
                        "axis_angle": 90,
                        "__class__": "quam.components.pulses.SquarePulse"
                    },
                    "y90_Square": {
                        "length": "#../x180_Square/length",
                        "digital_marker": "ON",
                        "amplitude": 0.125,
                        "axis_angle": 90,
                        "__class__": "quam.components.pulses.SquarePulse"
                    },
                    "-y90_Square": {
                        "length": "#../x180_Square/length",
                        "digital_marker": "ON",
                        "amplitude": -0.125,
                        "axis_angle": 90,
                        "__class__": "quam.components.pulses.SquarePulse"
                    },
                    "x180": "#./x180_DragCosine",
                    "x90": "#./x90_DragCosine",
                    "-x90": "#./-x90_DragCosine",
                    "y180": "#./y180_DragCosine",
                    "y90": "#./y90_DragCosine",
                    "-y90": "#./-y90_DragCosine",
                    "saturation": {
                        "length": 20000,
                        "digital_marker": "ON",
                        "amplitude": 0.019504222775281042,
                        "axis_angle": 0,
                        "__class__": "quam.components.pulses.SquarePulse"
                    },
                    "EF_x180": {
                        "length": 32,
                        "digital_marker": "ON",
                        "axis_angle": 0,
                        "amplitude": 0.27207287874742714,
                        "alpha": -0.1477090444870001,
                        "anharmonicity": 209000000,
                        "__class__": "quam.components.pulses.DragCosinePulse"
                    }
                },
                "intermediate_frequency": -331077041.843331,
                "opx_output_I": "#/wiring/qubits/q0/xy/opx_output_I",
                "opx_output_Q": "#/wiring/qubits/q0/xy/opx_output_Q",
                "frequency_converter_up": "#/wiring/qubits/q0/xy/frequency_converter_up"
            },
            "z": {
                "operations": {
                    "const": {
                        "length": 100,
                        "amplitude": 0.1,
                        "__class__": "quam.components.pulses.SquarePulse"
                    },
                    "z0": {
                        "length": 32,
                        "amplitude": 0.0,
                        "__class__": "quam.components.pulses.SquarePulse"
                    },
                    "z90": {
                        "length": 32,
                        "amplitude": 0.01945148563116481,
                        "__class__": "quam.components.pulses.SquarePulse"
                    },
                    "z180": {
                        "length": 32,
                        "amplitude": 0.027811148890565553,
                        "__class__": "quam.components.pulses.SquarePulse"
                    },
                    "-z90": {
                        "length": 32,
                        "amplitude": 0.033690961395873416,
                        "__class__": "quam.components.pulses.SquarePulse"
                    }
                },
                "opx_output": "#/wiring/qubits/q0/z/opx_output",
                "joint_offset": -0.03371729310045478
            },
            "resonator": {
                "depletion_time": 2500,
                "confusion_matrix": [
                    [
                        0.802,
                        0.198
                    ],
                    [
                        0.209,
                        0.791
                    ]
                ],
                "GEF_frequency_shift": 50000,
                "gef_centers": [
                    [
                        -0.00034485886598902585,
                        -0.0004030275002201358
                    ],
                    [
                        -4.8691268490765216e-05,
                        -0.0003047816976052757
                    ],
                    [
                        -9.850803274971421e-05,
                        -0.0006916127257029604
                    ]
                ],
                "gef_confusion_matrix": [
                    [
                        0.781,
                        0.1495,
                        0.0695
                    ],
                    [
                        0.153,
                        0.781,
                        0.066
                    ],
                    [
                        0.133,
                        0.092,
                        0.775
                    ]
                ],
                "operations": {
                    "readout": {
                        "length": 1500,
                        "amplitude": 0.016331557519721318,
                        "threshold": -0.00012345766835620146,
                        "rus_exit_threshold": -0.00029811153270808006,
                        "integration_weights_angle": -535.4517886616055,
                        "__class__": "quam.components.pulses.SquareReadoutPulse"
                    },
                    "const": {
                        "length": 100,
                        "amplitude": 0.125,
                        "__class__": "quam.components.pulses.SquarePulse"
                    }
                },
                "intermediate_frequency": -213081773,
                "opx_input_I": "#/wiring/qubits/q0/rr/opx_input_I",
                "opx_input_Q": "#/wiring/qubits/q0/rr/opx_input_Q",
                "time_of_flight": 296,
                "opx_input_offset_I": 0.0,
                "opx_input_offset_Q": 0.0,
                "input_gain": 10,
                "frequency_converter_down": "#/wiring/qubits/q0/rr/frequency_converter_down",
                "opx_output_I": "#/wiring/qubits/q0/rr/opx_output_I",
                "opx_output_Q": "#/wiring/qubits/q0/rr/opx_output_Q",
                "frequency_converter_up": "#/wiring/qubits/q0/rr/frequency_converter_up"
            },
            "anharmonicity": 214000000,
            "freq_vs_flux_01_quad_term": -21271975454.450764,
            "T1": 5.633926695167223e-05,
            "T2ramsey": 3.886231685694783e-06,
            "phi0_current": 33.13161776022881,
            "phi0_voltage": 0.6626323552045763,
            "GEF_frequency_shift": 250000,
            "chi": -300000.0,
            "grid_location": "0,2"
        },
        "q1": {
            "id": "q1",
            "xy": {
                "operations": {
                    "x180_DragCosine": {
                        "length": 32,
                        "digital_marker": "ON",
                        "axis_angle": 0,
                        "amplitude": 0.1003097850019761,
                        "alpha": -0.45281408225653225,
                        "anharmonicity": "#/qubits/q1/anharmonicity",
                        "detuning": 1700000.0,
                        "__class__": "quam.components.pulses.DragCosinePulse"
                    },
                    "x90_DragCosine": {
                        "length": "#../x180_DragCosine/length",
                        "digital_marker": "ON",
                        "axis_angle": 0,
                        "amplitude": 0.05015489250098805,
                        "alpha": "#../x180_DragCosine/alpha",
                        "anharmonicity": "#../x180_DragCosine/anharmonicity",
                        "detuning": 300000.0,
                        "__class__": "quam.components.pulses.DragCosinePulse"
                    },
                    "-x90_DragCosine": {
                        "length": "#../x180_DragCosine/length",
                        "digital_marker": "ON",
                        "axis_angle": 3.141592653589793,
                        "amplitude": "#../x90_DragCosine/amplitude",
                        "alpha": "#../x90_DragCosine/alpha",
                        "anharmonicity": "#../x180_DragCosine/anharmonicity",
                        "detuning": "#../x90_DragCosine/detuning",
                        "__class__": "quam.components.pulses.DragCosinePulse"
                    },
                    "y180_DragCosine": {
                        "length": "#../x180_DragCosine/length",
                        "digital_marker": "ON",
                        "axis_angle": 1.5707963267948966,
                        "amplitude": "#../x180_DragCosine/amplitude",
                        "alpha": "#../x180_DragCosine/alpha",
                        "anharmonicity": "#../x180_DragCosine/anharmonicity",
                        "detuning": "#../x180_DragCosine/detuning",
                        "__class__": "quam.components.pulses.DragCosinePulse"
                    },
                    "y90_DragCosine": {
                        "length": "#../x90_DragCosine/length",
                        "digital_marker": "ON",
                        "axis_angle": 1.5707963267948966,
                        "amplitude": "#../x90_DragCosine/amplitude",
                        "alpha": "#../x90_DragCosine/alpha",
                        "anharmonicity": "#../x180_DragCosine/anharmonicity",
                        "detuning": "#../x90_DragCosine/detuning",
                        "__class__": "quam.components.pulses.DragCosinePulse"
                    },
                    "-y90_DragCosine": {
                        "length": "#../x180_DragCosine/length",
                        "digital_marker": "ON",
                        "axis_angle": -1.5707963267948966,
                        "amplitude": "#../x90_DragCosine/amplitude",
                        "alpha": "#../x90_DragCosine/alpha",
                        "anharmonicity": "#../x180_DragCosine/anharmonicity",
                        "detuning": "#../x90_DragCosine/detuning",
                        "__class__": "quam.components.pulses.DragCosinePulse"
                    },
                    "x180_Square": {
                        "length": 100,
                        "digital_marker": "ON",
                        "amplitude": 0.25,
                        "axis_angle": 0,
                        "__class__": "quam.components.pulses.SquarePulse"
                    },
                    "x90_Square": {
                        "length": "#../x180_Square/length",
                        "digital_marker": "ON",
                        "amplitude": 0.125,
                        "axis_angle": 0,
                        "__class__": "quam.components.pulses.SquarePulse"
                    },
                    "-x90_Square": {
                        "length": "#../x180_Square/length",
                        "digital_marker": "ON",
                        "amplitude": -0.125,
                        "axis_angle": 0,
                        "__class__": "quam.components.pulses.SquarePulse"
                    },
                    "y180_Square": {
                        "length": "#../x180_Square/length",
                        "digital_marker": "ON",
                        "amplitude": 0.25,
                        "axis_angle": 90,
                        "__class__": "quam.components.pulses.SquarePulse"
                    },
                    "y90_Square": {
                        "length": "#../x180_Square/length",
                        "digital_marker": "ON",
                        "amplitude": 0.125,
                        "axis_angle": 90,
                        "__class__": "quam.components.pulses.SquarePulse"
                    },
                    "-y90_Square": {
                        "length": "#../x180_Square/length",
                        "digital_marker": "ON",
                        "amplitude": -0.125,
                        "axis_angle": 90,
                        "__class__": "quam.components.pulses.SquarePulse"
                    },
                    "x180": "#./x180_DragCosine",
                    "x90": "#./x90_DragCosine",
                    "-x90": "#./-x90_DragCosine",
                    "y180": "#./y180_DragCosine",
                    "y90": "#./y90_DragCosine",
                    "-y90": "#./-y90_DragCosine",
                    "saturation": {
                        "length": 20000,
                        "digital_marker": "ON",
                        "amplitude": 0.014296043168982569,
                        "axis_angle": 0,
                        "__class__": "quam.components.pulses.SquarePulse"
                    },
                    "EF_x180": {
                        "length": 32,
                        "digital_marker": "ON",
                        "axis_angle": 0,
                        "amplitude": 0.10059580742487743,
                        "alpha": -0.45281408225653225,
                        "anharmonicity": 206000000,
                        "__class__": "quam.components.pulses.DragCosinePulse"
                    }
                },
                "intermediate_frequency": -217256496.28811386,
                "opx_output_I": "#/wiring/qubits/q1/xy/opx_output_I",
                "opx_output_Q": "#/wiring/qubits/q1/xy/opx_output_Q",
                "frequency_converter_up": "#/wiring/qubits/q1/xy/frequency_converter_up"
            },
            "z": {
                "operations": {
                    "const": {
                        "length": 100,
                        "amplitude": 0.1,
                        "__class__": "quam.components.pulses.SquarePulse"
                    },
                    "z0": {
                        "length": 32,
                        "amplitude": 0.0,
                        "__class__": "quam.components.pulses.SquarePulse"
                    },
                    "z90": {
                        "length": 32,
                        "amplitude": 0.018371761544352494,
                        "__class__": "quam.components.pulses.SquarePulse"
                    },
                    "z180": {
                        "length": 32,
                        "amplitude": 0.0260335575293892,
                        "__class__": "quam.components.pulses.SquarePulse"
                    },
                    "-z90": {
                        "length": 32,
                        "amplitude": 0.03182082441935859,
                        "__class__": "quam.components.pulses.SquarePulse"
                    }
                },
                "opx_output": "#/wiring/qubits/q1/z/opx_output",
                "joint_offset": -0.04060852406280037
            },
            "resonator": {
                "depletion_time": 2500,
                "confusion_matrix": [
                    [
                        0.863,
                        0.137
                    ],
                    [
                        0.142,
                        0.858
                    ]
                ],
                "GEF_frequency_shift": -200000,
                "gef_centers": [
                    [
                        -2.4222762728989223e-05,
                        -0.0011577219514269917
                    ],
                    [
                        1.639921641796128e-05,
                        -0.0011417151200831433
                    ],
                    [
                        -1.2654529471590938e-05,
                        -0.0011172833779851115
                    ]
                ],
                "gef_confusion_matrix": [
                    [
                        0.3835,
                        0.2315,
                        0.385
                    ],
                    [
                        0.273,
                        0.189,
                        0.538
                    ],
                    [
                        0.258,
                        0.4055,
                        0.3365
                    ]
                ],
                "operations": {
                    "readout": {
                        "length": 1500,
                        "amplitude": 0.0237143235630474,
                        "threshold": -4.8884449683370146e-05,
                        "rus_exit_threshold": -0.00043936172110671024,
                        "integration_weights_angle": -548.7350568258898,
                        "__class__": "quam.components.pulses.SquareReadoutPulse"
                    },
                    "const": {
                        "length": 100,
                        "amplitude": 0.125,
                        "__class__": "quam.components.pulses.SquarePulse"
                    }
                },
                "intermediate_frequency": -67159104,
                "opx_input_I": "#/wiring/qubits/q1/rr/opx_input_I",
                "opx_input_Q": "#/wiring/qubits/q1/rr/opx_input_Q",
                "time_of_flight": 296,
                "opx_input_offset_I": 0.0,
                "opx_input_offset_Q": 0.0,
                "input_gain": 10,
                "frequency_converter_down": "#/wiring/qubits/q1/rr/frequency_converter_down",
                "opx_output_I": "#/wiring/qubits/q1/rr/opx_output_I",
                "opx_output_Q": "#/wiring/qubits/q1/rr/opx_output_Q",
                "frequency_converter_up": "#/wiring/qubits/q1/rr/frequency_converter_up"
            },
            "anharmonicity": 217000000,
            "freq_vs_flux_01_quad_term": -20970339507.567898,
            "T1": 5.109741356272203e-05,
            "T2ramsey": 6.205994651540559e-06,
            "phi0_current": 32.889895121907706,
            "phi0_voltage": 0.6577979024381542,
            "GEF_frequency_shift": 50000,
            "chi": -300000.0,
            "grid_location": "2,2"
        },
        "q2": {
            "id": "q2",
            "xy": {
                "operations": {
                    "x180_DragCosine": {
                        "length": 32,
                        "digital_marker": "ON",
                        "axis_angle": 0,
                        "amplitude": 0.18779986989263844,
                        "alpha": -0.8103496685208672,
                        "anharmonicity": "#/qubits/q2/anharmonicity",
                        "detuning": 950000.0,
                        "__class__": "quam.components.pulses.DragCosinePulse"
                    },
                    "x90_DragCosine": {
                        "length": "#../x180_DragCosine/length",
                        "digital_marker": "ON",
                        "axis_angle": 0,
                        "amplitude": 0.09389993494631922,
                        "alpha": "#../x180_DragCosine/alpha",
                        "anharmonicity": "#../x180_DragCosine/anharmonicity",
                        "detuning": 100000.0,
                        "__class__": "quam.components.pulses.DragCosinePulse"
                    },
                    "-x90_DragCosine": {
                        "length": "#../x180_DragCosine/length",
                        "digital_marker": "ON",
                        "axis_angle": 3.141592653589793,
                        "amplitude": "#../x90_DragCosine/amplitude",
                        "alpha": "#../x90_DragCosine/alpha",
                        "anharmonicity": "#../x180_DragCosine/anharmonicity",
                        "detuning": "#../x90_DragCosine/detuning",
                        "__class__": "quam.components.pulses.DragCosinePulse"
                    },
                    "y180_DragCosine": {
                        "length": "#../x180_DragCosine/length",
                        "digital_marker": "ON",
                        "axis_angle": 1.5707963267948966,
                        "amplitude": "#../x180_DragCosine/amplitude",
                        "alpha": "#../x180_DragCosine/alpha",
                        "anharmonicity": "#../x180_DragCosine/anharmonicity",
                        "detuning": "#../x180_DragCosine/detuning",
                        "__class__": "quam.components.pulses.DragCosinePulse"
                    },
                    "y90_DragCosine": {
                        "length": "#../x90_DragCosine/length",
                        "digital_marker": "ON",
                        "axis_angle": 1.5707963267948966,
                        "amplitude": "#../x90_DragCosine/amplitude",
                        "alpha": "#../x90_DragCosine/alpha",
                        "anharmonicity": "#../x180_DragCosine/anharmonicity",
                        "detuning": "#../x90_DragCosine/detuning",
                        "__class__": "quam.components.pulses.DragCosinePulse"
                    },
                    "-y90_DragCosine": {
                        "length": "#../x180_DragCosine/length",
                        "digital_marker": "ON",
                        "axis_angle": -1.5707963267948966,
                        "amplitude": "#../x90_DragCosine/amplitude",
                        "alpha": "#../x90_DragCosine/alpha",
                        "anharmonicity": "#../x180_DragCosine/anharmonicity",
                        "detuning": "#../x90_DragCosine/detuning",
                        "__class__": "quam.components.pulses.DragCosinePulse"
                    },
                    "x180_Square": {
                        "length": 100,
                        "digital_marker": "ON",
                        "amplitude": 0.25,
                        "axis_angle": 0,
                        "__class__": "quam.components.pulses.SquarePulse"
                    },
                    "x90_Square": {
                        "length": "#../x180_Square/length",
                        "digital_marker": "ON",
                        "amplitude": 0.125,
                        "axis_angle": 0,
                        "__class__": "quam.components.pulses.SquarePulse"
                    },
                    "-x90_Square": {
                        "length": "#../x180_Square/length",
                        "digital_marker": "ON",
                        "amplitude": -0.125,
                        "axis_angle": 0,
                        "__class__": "quam.components.pulses.SquarePulse"
                    },
                    "y180_Square": {
                        "length": "#../x180_Square/length",
                        "digital_marker": "ON",
                        "amplitude": 0.25,
                        "axis_angle": 90,
                        "__class__": "quam.components.pulses.SquarePulse"
                    },
                    "y90_Square": {
                        "length": "#../x180_Square/length",
                        "digital_marker": "ON",
                        "amplitude": 0.125,
                        "axis_angle": 90,
                        "__class__": "quam.components.pulses.SquarePulse"
                    },
                    "-y90_Square": {
                        "length": "#../x180_Square/length",
                        "digital_marker": "ON",
                        "amplitude": -0.125,
                        "axis_angle": 90,
                        "__class__": "quam.components.pulses.SquarePulse"
                    },
                    "x180": "#./x180_DragCosine",
                    "x90": "#./x90_DragCosine",
                    "-x90": "#./-x90_DragCosine",
                    "y180": "#./y180_DragCosine",
                    "y90": "#./y90_DragCosine",
                    "-y90": "#./-y90_DragCosine",
                    "saturation": {
                        "length": 20000,
                        "digital_marker": "ON",
                        "amplitude": 0.03603842137330526,
                        "axis_angle": 0,
                        "__class__": "quam.components.pulses.SquarePulse"
                    },
                    "EF_x180": {
                        "length": 32,
                        "digital_marker": "ON",
                        "axis_angle": 0,
                        "amplitude": 0.08371184742690173,
                        "alpha": -0.8103496685208672,
                        "anharmonicity": 196500000,
                        "__class__": "quam.components.pulses.DragCosinePulse"
                    }
                },
                "intermediate_frequency": 363392882.4822296,
                "opx_output_I": "#/wiring/qubits/q2/xy/opx_output_I",
                "opx_output_Q": "#/wiring/qubits/q2/xy/opx_output_Q",
                "frequency_converter_up": "#/wiring/qubits/q2/xy/frequency_converter_up"
            },
            "z": {
                "operations": {
                    "const": {
                        "length": 100,
                        "amplitude": 0.1,
                        "__class__": "quam.components.pulses.SquarePulse"
                    },
                    "z0": {
                        "length": 32,
                        "amplitude": 0.0,
                        "__class__": "quam.components.pulses.SquarePulse"
                    },
                    "z90": {
                        "length": 32,
                        "amplitude": 0.018154431080104415,
                        "__class__": "quam.components.pulses.SquarePulse"
                    },
                    "z180": {
                        "length": 32,
                        "amplitude": 0.02611070477571238,
                        "__class__": "quam.components.pulses.SquarePulse"
                    },
                    "-z90": {
                        "length": 32,
                        "amplitude": 0.031444397013248374,
                        "__class__": "quam.components.pulses.SquarePulse"
                    }
                },
                "opx_output": "#/wiring/qubits/q2/z/opx_output",
                "joint_offset": 0.009524176638114633
            },
            "resonator": {
                "depletion_time": 2500,
                "confusion_matrix": [
                    [
                        0.833,
                        0.167
                    ],
                    [
                        0.14,
                        0.86
                    ]
                ],
                "GEF_frequency_shift": 50000,
                "gef_centers": [
                    [
                        -0.0006133387142295004,
                        -0.0003213428806189048
                    ],
                    [
                        -0.00023001170363017143,
                        -0.0002079808582485741
                    ],
                    [
                        -7.169120893450341e-05,
                        -0.0005309891344794284
                    ]
                ],
                "gef_confusion_matrix": [
                    [
                        0.8285,
                        0.146,
                        0.0255
                    ],
                    [
                        0.1655,
                        0.76,
                        0.0745
                    ],
                    [
                        0.1205,
                        0.128,
                        0.7515
                    ]
                ],
                "operations": {
                    "readout": {
                        "length": 1500,
                        "amplitude": 0.01700491770026253,
                        "threshold": -0.0003154761337455237,
                        "rus_exit_threshold": -0.0005732433857979782,
                        "integration_weights_angle": -575.7219156239314,
                        "__class__": "quam.components.pulses.SquareReadoutPulse"
                    },
                    "const": {
                        "length": 100,
                        "amplitude": 0.125,
                        "__class__": "quam.components.pulses.SquarePulse"
                    }
                },
                "intermediate_frequency": 86049697,
                "opx_input_I": "#/wiring/qubits/q2/rr/opx_input_I",
                "opx_input_Q": "#/wiring/qubits/q2/rr/opx_input_Q",
                "time_of_flight": 296,
                "opx_input_offset_I": 0.0,
                "opx_input_offset_Q": 0.0,
                "input_gain": 10,
                "frequency_converter_down": "#/wiring/qubits/q2/rr/frequency_converter_down",
                "opx_output_I": "#/wiring/qubits/q2/rr/opx_output_I",
                "opx_output_Q": "#/wiring/qubits/q2/rr/opx_output_Q",
                "frequency_converter_up": "#/wiring/qubits/q2/rr/frequency_converter_up"
            },
            "anharmonicity": 205500000,
            "freq_vs_flux_01_quad_term": -23427264013.63086,
            "T1": 4.589418554059009e-05,
            "T2ramsey": 8.84522843266331e-06,
            "phi0_current": 37.24650662137818,
            "phi0_voltage": 0.7449301324275637,
            "GEF_frequency_shift": 200000,
            "chi": -200000.0,
            "grid_location": "1,1"
        },
        "q3": {
            "id": "q3",
            "xy": {
                "operations": {
                    "x180_DragCosine": {
                        "length": 32,
                        "digital_marker": "ON",
                        "axis_angle": 0,
                        "amplitude": 0.23486331394014773,
                        "alpha": 0.0051871539720758945,
                        "anharmonicity": "#/qubits/q3/anharmonicity",
                        "detuning": 200000.0,
                        "__class__": "quam.components.pulses.DragCosinePulse"
                    },
                    "x90_DragCosine": {
                        "length": "#../x180_DragCosine/length",
                        "digital_marker": "ON",
                        "axis_angle": 0,
                        "amplitude": 0.11743165697007386,
                        "alpha": "#../x180_DragCosine/alpha",
                        "anharmonicity": "#../x180_DragCosine/anharmonicity",
                        "detuning": 100000.0,
                        "__class__": "quam.components.pulses.DragCosinePulse"
                    },
                    "-x90_DragCosine": {
                        "length": "#../x180_DragCosine/length",
                        "digital_marker": "ON",
                        "axis_angle": 3.141592653589793,
                        "amplitude": "#../x90_DragCosine/amplitude",
                        "alpha": "#../x90_DragCosine/alpha",
                        "anharmonicity": "#../x180_DragCosine/anharmonicity",
                        "detuning": "#../x90_DragCosine/detuning",
                        "__class__": "quam.components.pulses.DragCosinePulse"
                    },
                    "y180_DragCosine": {
                        "length": "#../x180_DragCosine/length",
                        "digital_marker": "ON",
                        "axis_angle": 1.5707963267948966,
                        "amplitude": "#../x180_DragCosine/amplitude",
                        "alpha": "#../x180_DragCosine/alpha",
                        "anharmonicity": "#../x180_DragCosine/anharmonicity",
                        "detuning": "#../x180_DragCosine/detuning",
                        "__class__": "quam.components.pulses.DragCosinePulse"
                    },
                    "y90_DragCosine": {
                        "length": "#../x90_DragCosine/length",
                        "digital_marker": "ON",
                        "axis_angle": 1.5707963267948966,
                        "amplitude": "#../x90_DragCosine/amplitude",
                        "alpha": "#../x90_DragCosine/alpha",
                        "anharmonicity": "#../x180_DragCosine/anharmonicity",
                        "detuning": "#../x90_DragCosine/detuning",
                        "__class__": "quam.components.pulses.DragCosinePulse"
                    },
                    "-y90_DragCosine": {
                        "length": "#../x180_DragCosine/length",
                        "digital_marker": "ON",
                        "axis_angle": -1.5707963267948966,
                        "amplitude": "#../x90_DragCosine/amplitude",
                        "alpha": "#../x90_DragCosine/alpha",
                        "anharmonicity": "#../x180_DragCosine/anharmonicity",
                        "detuning": "#../x90_DragCosine/detuning",
                        "__class__": "quam.components.pulses.DragCosinePulse"
                    },
                    "x180_Square": {
                        "length": 100,
                        "digital_marker": "ON",
                        "amplitude": 0.25,
                        "axis_angle": 0,
                        "__class__": "quam.components.pulses.SquarePulse"
                    },
                    "x90_Square": {
                        "length": "#../x180_Square/length",
                        "digital_marker": "ON",
                        "amplitude": 0.125,
                        "axis_angle": 0,
                        "__class__": "quam.components.pulses.SquarePulse"
                    },
                    "-x90_Square": {
                        "length": "#../x180_Square/length",
                        "digital_marker": "ON",
                        "amplitude": -0.125,
                        "axis_angle": 0,
                        "__class__": "quam.components.pulses.SquarePulse"
                    },
                    "y180_Square": {
                        "length": "#../x180_Square/length",
                        "digital_marker": "ON",
                        "amplitude": 0.25,
                        "axis_angle": 90,
                        "__class__": "quam.components.pulses.SquarePulse"
                    },
                    "y90_Square": {
                        "length": "#../x180_Square/length",
                        "digital_marker": "ON",
                        "amplitude": 0.125,
                        "axis_angle": 90,
                        "__class__": "quam.components.pulses.SquarePulse"
                    },
                    "-y90_Square": {
                        "length": "#../x180_Square/length",
                        "digital_marker": "ON",
                        "amplitude": -0.125,
                        "axis_angle": 90,
                        "__class__": "quam.components.pulses.SquarePulse"
                    },
                    "x180": "#./x180_DragCosine",
                    "x90": "#./x90_DragCosine",
                    "-x90": "#./-x90_DragCosine",
                    "y180": "#./y180_DragCosine",
                    "y90": "#./y90_DragCosine",
                    "-y90": "#./-y90_DragCosine",
                    "saturation": {
                        "length": 20000,
                        "digital_marker": "ON",
                        "amplitude": 0.045460199237951644,
                        "axis_angle": 0,
                        "__class__": "quam.components.pulses.SquarePulse"
                    },
                    "EF_x180": {
                        "length": 32,
                        "digital_marker": "ON",
                        "axis_angle": 0,
                        "amplitude": 0.2347478760611692,
                        "alpha": 0.0051871539720758945,
                        "anharmonicity": 190500000,
                        "__class__": "quam.components.pulses.DragCosinePulse"
                    }
                },
                "intermediate_frequency": -208699549.67351577,
                "opx_output_I": "#/wiring/qubits/q3/xy/opx_output_I",
                "opx_output_Q": "#/wiring/qubits/q3/xy/opx_output_Q",
                "frequency_converter_up": "#/wiring/qubits/q3/xy/frequency_converter_up"
            },
            "z": {
                "operations": {
                    "const": {
                        "length": 100,
                        "amplitude": 0.1,
                        "__class__": "quam.components.pulses.SquarePulse"
                    },
                    "z0": {
                        "length": 32,
                        "amplitude": 0.0,
                        "__class__": "quam.components.pulses.SquarePulse"
                    },
                    "z90": {
                        "length": 32,
                        "amplitude": 0.017082128579887525,
                        "__class__": "quam.components.pulses.SquarePulse"
                    },
                    "z180": {
                        "length": 32,
                        "amplitude": 0.024423513468908666,
                        "__class__": "quam.components.pulses.SquarePulse"
                    },
                    "-z90": {
                        "length": 32,
                        "amplitude": 0.029587114601789588,
                        "__class__": "quam.components.pulses.SquarePulse"
                    }
                },
                "opx_output": "#/wiring/qubits/q3/z/opx_output",
                "joint_offset": -0.03522669023296579
            },
            "resonator": {
                "depletion_time": 2500,
                "confusion_matrix": [
                    [
                        0.898,
                        0.102
                    ],
                    [
                        0.109,
                        0.891
                    ]
                ],
                "GEF_frequency_shift": -150000,
                "gef_centers": [
                    [
                        -0.00013984973837449826,
                        -0.0014262639253995336
                    ],
                    [
                        -7.102785985661177e-05,
                        -0.0008905545993174131
                    ],
                    [
                        0.0005129363160746587,
                        -0.0007378190898073138
                    ]
                ],
                "gef_confusion_matrix": [
                    [
                        0.8835,
                        0.1005,
                        0.016
                    ],
                    [
                        0.1225,
                        0.857,
                        0.0205
                    ],
                    [
                        0.101,
                        0.1205,
                        0.7785
                    ]
                ],
                "operations": {
                    "readout": {
                        "length": 1500,
                        "amplitude": 0.04826767485375295,
                        "threshold": -0.0001324019570827302,
                        "rus_exit_threshold": -0.00048765086363968224,
                        "integration_weights_angle": -564.5613551586204,
                        "__class__": "quam.components.pulses.SquareReadoutPulse"
                    },
                    "const": {
                        "length": 100,
                        "amplitude": 0.125,
                        "__class__": "quam.components.pulses.SquarePulse"
                    }
                },
                "intermediate_frequency": 263900000,
                "opx_input_I": "#/wiring/qubits/q3/rr/opx_input_I",
                "opx_input_Q": "#/wiring/qubits/q3/rr/opx_input_Q",
                "time_of_flight": 296,
                "opx_input_offset_I": 0.0,
                "opx_input_offset_Q": 0.0,
                "input_gain": 10,
                "frequency_converter_down": "#/wiring/qubits/q3/rr/frequency_converter_down",
                "opx_output_I": "#/wiring/qubits/q3/rr/opx_output_I",
                "opx_output_Q": "#/wiring/qubits/q3/rr/opx_output_Q",
                "frequency_converter_up": "#/wiring/qubits/q3/rr/frequency_converter_up"
            },
            "anharmonicity": 197500000,
            "freq_vs_flux_01_quad_term": -25844077306.14595,
            "T1": 3.432181658112503e-05,
            "T2ramsey": 3.1112026360805395e-06,
            "phi0_current": 42.229720068471536,
            "phi0_voltage": 0.8445944013694308,
            "GEF_frequency_shift": 150000,
            "chi": -150000.0,
            "grid_location": "0,0"
        },
        "q4": {
            "id": "q4",
            "xy": {
                "operations": {
                    "x180_DragCosine": {
                        "length": 32,
                        "digital_marker": "ON",
                        "axis_angle": 0,
                        "amplitude": 0.17535708011937895,
                        "alpha": -1.815213890059611,
                        "anharmonicity": "#/qubits/q4/anharmonicity",
                        "detuning": -100000.0,
                        "__class__": "quam.components.pulses.DragCosinePulse"
                    },
                    "x90_DragCosine": {
                        "length": "#../x180_DragCosine/length",
                        "digital_marker": "ON",
                        "axis_angle": 0,
                        "amplitude": 0.08767854005968947,
                        "alpha": "#../x180_DragCosine/alpha",
                        "anharmonicity": "#../x180_DragCosine/anharmonicity",
                        "detuning": 500000.0,
                        "__class__": "quam.components.pulses.DragCosinePulse"
                    },
                    "-x90_DragCosine": {
                        "length": "#../x180_DragCosine/length",
                        "digital_marker": "ON",
                        "axis_angle": 3.141592653589793,
                        "amplitude": "#../x90_DragCosine/amplitude",
                        "alpha": "#../x90_DragCosine/alpha",
                        "anharmonicity": "#../x180_DragCosine/anharmonicity",
                        "detuning": "#../x90_DragCosine/detuning",
                        "__class__": "quam.components.pulses.DragCosinePulse"
                    },
                    "y180_DragCosine": {
                        "length": "#../x180_DragCosine/length",
                        "digital_marker": "ON",
                        "axis_angle": 1.5707963267948966,
                        "amplitude": "#../x180_DragCosine/amplitude",
                        "alpha": "#../x180_DragCosine/alpha",
                        "anharmonicity": "#../x180_DragCosine/anharmonicity",
                        "detuning": "#../x180_DragCosine/detuning",
                        "__class__": "quam.components.pulses.DragCosinePulse"
                    },
                    "y90_DragCosine": {
                        "length": "#../x90_DragCosine/length",
                        "digital_marker": "ON",
                        "axis_angle": 1.5707963267948966,
                        "amplitude": "#../x90_DragCosine/amplitude",
                        "alpha": "#../x90_DragCosine/alpha",
                        "anharmonicity": "#../x180_DragCosine/anharmonicity",
                        "detuning": "#../x90_DragCosine/detuning",
                        "__class__": "quam.components.pulses.DragCosinePulse"
                    },
                    "-y90_DragCosine": {
                        "length": "#../x180_DragCosine/length",
                        "digital_marker": "ON",
                        "axis_angle": -1.5707963267948966,
                        "amplitude": "#../x90_DragCosine/amplitude",
                        "alpha": "#../x90_DragCosine/alpha",
                        "anharmonicity": "#../x180_DragCosine/anharmonicity",
                        "detuning": "#../x90_DragCosine/detuning",
                        "__class__": "quam.components.pulses.DragCosinePulse"
                    },
                    "x180_Square": {
                        "length": 100,
                        "digital_marker": "ON",
                        "amplitude": 0.25,
                        "axis_angle": 0,
                        "__class__": "quam.components.pulses.SquarePulse"
                    },
                    "x90_Square": {
                        "length": "#../x180_Square/length",
                        "digital_marker": "ON",
                        "amplitude": 0.125,
                        "axis_angle": 0,
                        "__class__": "quam.components.pulses.SquarePulse"
                    },
                    "-x90_Square": {
                        "length": "#../x180_Square/length",
                        "digital_marker": "ON",
                        "amplitude": -0.125,
                        "axis_angle": 0,
                        "__class__": "quam.components.pulses.SquarePulse"
                    },
                    "y180_Square": {
                        "length": "#../x180_Square/length",
                        "digital_marker": "ON",
                        "amplitude": 0.25,
                        "axis_angle": 90,
                        "__class__": "quam.components.pulses.SquarePulse"
                    },
                    "y90_Square": {
                        "length": "#../x180_Square/length",
                        "digital_marker": "ON",
                        "amplitude": 0.125,
                        "axis_angle": 90,
                        "__class__": "quam.components.pulses.SquarePulse"
                    },
                    "-y90_Square": {
                        "length": "#../x180_Square/length",
                        "digital_marker": "ON",
                        "amplitude": -0.125,
                        "axis_angle": 90,
                        "__class__": "quam.components.pulses.SquarePulse"
                    },
                    "x180": "#./x180_DragCosine",
                    "x90": "#./x90_DragCosine",
                    "-x90": "#./-x90_DragCosine",
                    "y180": "#./y180_DragCosine",
                    "y90": "#./y90_DragCosine",
                    "-y90": "#./-y90_DragCosine",
                    "saturation": {
                        "length": 20000,
                        "digital_marker": "ON",
                        "amplitude": 0.031972013720578944,
                        "axis_angle": 0,
                        "__class__": "quam.components.pulses.SquarePulse"
                    },
                    "EF_x180": {
                        "length": 32,
                        "digital_marker": "ON",
                        "axis_angle": 0,
                        "amplitude": 0.11081718698264056,
                        "alpha": -1.815213890059611,
                        "anharmonicity": 197000000,
                        "__class__": "quam.components.pulses.DragCosinePulse"
                    }
                },
                "intermediate_frequency": 194417861.43653104,
                "opx_output_I": "#/wiring/qubits/q4/xy/opx_output_I",
                "opx_output_Q": "#/wiring/qubits/q4/xy/opx_output_Q",
                "frequency_converter_up": "#/wiring/qubits/q4/xy/frequency_converter_up"
            },
            "z": {
                "operations": {
                    "const": {
                        "length": 100,
                        "amplitude": 0.1,
                        "__class__": "quam.components.pulses.SquarePulse"
                    },
                    "z0": {
                        "length": 32,
                        "amplitude": 0.0,
                        "__class__": "quam.components.pulses.SquarePulse"
                    },
                    "z90": {
                        "length": 32,
                        "amplitude": 0.01641529544165795,
                        "__class__": "quam.components.pulses.SquarePulse"
                    },
                    "z180": {
                        "length": 32,
                        "amplitude": 0.02323794817739788,
                        "__class__": "quam.components.pulses.SquarePulse"
                    },
                    "-z90": {
                        "length": 32,
                        "amplitude": 0.028432125726205362,
                        "__class__": "quam.components.pulses.SquarePulse"
                    }
                },
                "opx_output": "#/wiring/qubits/q4/z/opx_output",
                "joint_offset": -0.03182497810768545
            },
            "resonator": {
                "depletion_time": 2500,
                "confusion_matrix": [
                    [
                        0.939,
                        0.061
                    ],
                    [
                        0.095,
                        0.905
                    ]
                ],
                "GEF_frequency_shift": 250000,
                "gef_centers": [
                    [
                        -0.0007690698569498061,
                        0.0012508022818077513
                    ],
                    [
                        -0.00020959847590247842,
                        0.0009931966763100078
                    ],
                    [
                        -0.00023307704486443475,
                        0.0002834908618375777
                    ]
                ],
                "gef_confusion_matrix": [
                    [
                        0.7915,
                        0.1045,
                        0.104
                    ],
                    [
                        0.2205,
                        0.639,
                        0.1405
                    ],
                    [
                        0.204,
                        0.147,
                        0.649
                    ]
                ],
                "operations": {
                    "readout": {
                        "length": 1500,
                        "amplitude": 0.04596610169491525,
                        "threshold": -0.0009058061656996368,
                        "rus_exit_threshold": -0.0011162055726937296,
                        "integration_weights_angle": -505.9013741378774,
                        "__class__": "quam.components.pulses.SquareReadoutPulse"
                    },
                    "const": {
                        "length": 100,
                        "amplitude": 0.125,
                        "__class__": "quam.components.pulses.SquarePulse"
                    }
                },
                "intermediate_frequency": -225800000,
                "opx_input_I": "#/wiring/qubits/q4/rr/opx_input_I",
                "opx_input_Q": "#/wiring/qubits/q4/rr/opx_input_Q",
                "time_of_flight": 296,
                "opx_input_offset_I": 0.0,
                "opx_input_offset_Q": 0.0,
                "input_gain": 10,
                "frequency_converter_down": "#/wiring/qubits/q4/rr/frequency_converter_down",
                "opx_output_I": "#/wiring/qubits/q4/rr/opx_output_I",
                "opx_output_Q": "#/wiring/qubits/q4/rr/opx_output_Q",
                "frequency_converter_up": "#/wiring/qubits/q4/rr/frequency_converter_up"
            },
            "anharmonicity": 200000000,
            "freq_vs_flux_01_quad_term": -19084791753.74047,
            "T1": 4.106197470698975e-05,
            "T2ramsey": 5.1713427316491585e-06,
            "phi0_current": 42.185449982477124,
            "phi0_voltage": 0.8437089996495425,
            "GEF_frequency_shift": 600000,
            "chi": -150000.0,
            "grid_location": "2,0"
        }
    },
    "qubit_pairs": {
        "q0-q2": {
            "id": "q0-q2",
            "qubit_control": "#/qubits/q2",
            "qubit_target": "#/qubits/q0",
            "gates": {
                "Cz_unipolar": {
                    "flux_pulse_control": {
                        "length": 40,
                        "id": "flux_pulse_control_q0",
                        "amplitude": 0.14488693679675899,
                        "zero_padding": 1,
                        "__class__": "quam_libs.lib.pulses.FluxPulse"
                    },
                    "phase_shift_control": 0.23075754621781097,
                    "phase_shift_target": 0.9272040605168345,
                    "__class__": "quam_libs.components.gates.two_qubit_gates.CZGate"
                },
                "Cz": "#./Cz_unipolar"
            },
            "J2": 12735937.561737923,
            "detuning": 491709711.2569441,
            "confusion": [
                [
                    0.8755,
                    0.314,
                    0.302,
                    0.093
                ],
                [
                    0.086,
                    0.656,
                    0.0375,
                    0.2525
                ],
                [
                    0.0345,
                    0.01,
                    0.59,
                    0.2115
                ],
                [
                    0.004,
                    0.02,
                    0.0705,
                    0.443
                ]
            ]
        },
        "q1-q2": {
            "id": "q1-q2",
            "qubit_control": "#/qubits/q2",
            "qubit_target": "#/qubits/q1",
            "gates": {
                "Cz_unipolar": {
                    "flux_pulse_control": {
                        "length": 40,
                        "id": "flux_pulse_control_qubit2",
                        "amplitude": 0.1335570177577635,
                        "zero_padding": 2,
                        "__class__": "quam_libs.lib.pulses.FluxPulse"
                    },
                    "phase_shift_control": 0.5598164314712646,
                    "phase_shift_target": 0.6692907363359615,
                    "__class__": "quam_libs.components.gates.two_qubit_gates.CZGate"
                },
                "Cz": "#./Cz_unipolar"
            },
            "J2": 13007691.031622594,
            "detuning": 416989271.61498356,
            "confusion": [
                [
                    0.826,
                    0.588,
                    0.263,
                    0.19
                ],
                [
                    0.115,
                    0.367,
                    0.057,
                    0.131
                ],
                [
                    0.027,
                    0.018,
                    0.5945,
                    0.428
                ],
                [
                    0.032,
                    0.027,
                    0.0855,
                    0.251
                ]
            ]
        },
        "q2-q3": {
            "id": "q2-q3",
            "qubit_control": "#/qubits/q3",
            "qubit_target": "#/qubits/q2",
            "gates": {
                "Cz_unipolar": {
                    "flux_pulse_control": {
                        "length": 44,
                        "id": "flux_pulse_control_q2",
                        "amplitude": 0.1299316730799836,
                        "zero_padding": 4,
                        "__class__": "quam_libs.lib.pulses.FluxPulse"
                    },
                    "phase_shift_control": 0.8927361773036087,
                    "phase_shift_target": 0.9612734245519532,
                    "__class__": "quam_libs.components.gates.two_qubit_gates.CZGate"
                },
                "Cz": "#./Cz_unipolar"
            },
            "J2": 12342488.752572248,
            "detuning": 432293922.48273355,
            "confusion": [
                [
                    0.9325,
                    0.309,
                    0.165,
                    0.0525
                ],
                [
                    0.038,
                    0.663,
                    0.008,
                    0.12
                ],
                [
                    0.0275,
                    0.0105,
                    0.802,
                    0.2545
                ],
                [
                    0.002,
                    0.0175,
                    0.025,
                    0.573
                ]
            ]
        },
        "q2-q4": {
            "id": "q2-q4",
            "qubit_control": "#/qubits/q4",
            "qubit_target": "#/qubits/q2",
            "gates": {
                "Cz_unipolar": {
                    "flux_pulse_control": {
                        "length": 40,
                        "id": "flux_pulse_control_q2",
                        "amplitude": 0.18241139906954645,
                        "zero_padding": 2,
                        "__class__": "quam_libs.lib.pulses.FluxPulse"
                    },
                    "phase_shift_control": 0.9176630466030452,
                    "phase_shift_target": 0.9749407238009004,
                    "__class__": "quam_libs.components.gates.two_qubit_gates.CZGate"
                },
                "Cz": "#./Cz_unipolar"
            },
            "J2": 13140900.70712887,
            "detuning": 620181615.3305641,
            "confusion": [
                [
                    0.8385,
                    0.298,
                    0.734,
                    0.216
                ],
                [
                    0.026,
                    0.655,
                    0.02,
                    0.476
                ],
                [
                    0.1295,
                    0.0125,
                    0.2405,
                    0.099
                ],
                [
                    0.006,
                    0.0345,
                    0.0055,
                    0.209
                ]
            ]
        }
    },
    "active_qubit_names": [
        "q0",
        "q1",
        "q2",
        "q3",
        "q4"
    ],
    "active_qubit_pair_names": [
        "q0-q2",
        "q1-q2",
        "q2-q3",
        "q2-q4"
    ],
    "ports": {
        "analog_outputs": {
            "con1": {
                "1": {
                    "controller_id": "con1",
                    "port_id": 1,
                    "__class__": "quam.components.ports.analog_outputs.OPXPlusAnalogOutputPort"
                },
                "2": {
                    "controller_id": "con1",
                    "port_id": 2,
                    "__class__": "quam.components.ports.analog_outputs.OPXPlusAnalogOutputPort"
                },
                "9": {
                    "controller_id": "con1",
                    "port_id": 9,
                    "__class__": "quam.components.ports.analog_outputs.OPXPlusAnalogOutputPort"
                },
                "10": {
                    "controller_id": "con1",
                    "port_id": 10,
                    "__class__": "quam.components.ports.analog_outputs.OPXPlusAnalogOutputPort"
                },
                "7": {
                    "controller_id": "con1",
                    "port_id": 7,
                    "__class__": "quam.components.ports.analog_outputs.OPXPlusAnalogOutputPort"
                },
                "8": {
                    "controller_id": "con1",
                    "port_id": 8,
                    "__class__": "quam.components.ports.analog_outputs.OPXPlusAnalogOutputPort"
                },
                "5": {
                    "controller_id": "con1",
                    "port_id": 5,
                    "__class__": "quam.components.ports.analog_outputs.OPXPlusAnalogOutputPort"
                },
                "6": {
                    "controller_id": "con1",
                    "port_id": 6,
                    "__class__": "quam.components.ports.analog_outputs.OPXPlusAnalogOutputPort"
                },
                "3": {
                    "controller_id": "con1",
                    "port_id": 3,
                    "__class__": "quam.components.ports.analog_outputs.OPXPlusAnalogOutputPort"
                },
                "4": {
                    "controller_id": "con1",
                    "port_id": 4,
                    "__class__": "quam.components.ports.analog_outputs.OPXPlusAnalogOutputPort"
                }
            },
            "con2": {
                "3": {
                    "controller_id": "con2",
                    "port_id": 3,
                    "__class__": "quam.components.ports.analog_outputs.OPXPlusAnalogOutputPort"
                },
                "4": {
                    "controller_id": "con2",
                    "port_id": 4,
                    "__class__": "quam.components.ports.analog_outputs.OPXPlusAnalogOutputPort"
                },
                "5": {
                    "controller_id": "con2",
                    "port_id": 5,
                    "crosstalk": {
                        "6": -0.020718111637107916,
                        "7": -0.04436269522501283,
                        "8": -0.014854711105917028,
                        "9": 0.0
                    },
                    "feedforward_filter": [],
                    "feedback_filter": [],
                    "__class__": "quam.components.ports.analog_outputs.OPXPlusAnalogOutputPort"
                },
                "6": {
                    "controller_id": "con2",
                    "port_id": 6,
                    "crosstalk": {
                        "5": -0.01519316807618339,
                        "7": -0.05204185502886357,
                        "8": -0.01663764037001517,
                        "9": 0.0
                    },
                    "feedforward_filter": [],
                    "feedback_filter": [],
                    "__class__": "quam.components.ports.analog_outputs.OPXPlusAnalogOutputPort"
                },
                "7": {
                    "controller_id": "con2",
                    "port_id": 7,
                    "crosstalk": {
                        "5": -0.021546439127658044,
                        "6": -0.035152988686189816,
                        "8": -0.023608067980049934,
                        "9": 0.0
                    },
                    "feedforward_filter": [],
                    "feedback_filter": [],
                    "__class__": "quam.components.ports.analog_outputs.OPXPlusAnalogOutputPort"
                },
                "8": {
                    "controller_id": "con2",
                    "port_id": 8,
                    "crosstalk": {
                        "5": -0.008985705417105801,
                        "6": -0.02154002257961968,
                        "7": -0.04979278852467497,
                        "9": 0.0
                    },
                    "feedforward_filter": [],
                    "feedback_filter": [],
                    "__class__": "quam.components.ports.analog_outputs.OPXPlusAnalogOutputPort"
                },
                "1": {
                    "controller_id": "con2",
                    "port_id": 1,
                    "__class__": "quam.components.ports.analog_outputs.OPXPlusAnalogOutputPort"
                },
                "2": {
                    "controller_id": "con2",
                    "port_id": 2,
                    "__class__": "quam.components.ports.analog_outputs.OPXPlusAnalogOutputPort"
                },
                "9": {
                    "controller_id": "con2",
                    "port_id": 9,
                    "crosstalk": {
                        "5": -0.01018548141509489,
                        "6": -0.015858021969311308,
                        "7": -0.05508554182512948,
                        "8": -0.011560865825304559
                    },
                    "feedforward_filter": [],
                    "feedback_filter": [],
                    "__class__": "quam.components.ports.analog_outputs.OPXPlusAnalogOutputPort"
                }
            }
        },
        "analog_inputs": {
            "con1": {
                "1": {
                    "controller_id": "con1",
                    "port_id": 1,
                    "offset": -0.1063435397135416,
                    "__class__": "quam.components.ports.analog_inputs.OPXPlusAnalogInputPort"
                },
                "2": {
                    "controller_id": "con1",
                    "port_id": 2,
                    "offset": -0.08838355989583335,
                    "__class__": "quam.components.ports.analog_inputs.OPXPlusAnalogInputPort"
                }
            },
            "con2": {
                "1": {
                    "controller_id": "con2",
                    "port_id": 1,
                    "offset": -0.1063435397135416,
                    "__class__": "quam.components.ports.analog_inputs.OPXPlusAnalogInputPort"
                },
                "2": {
                    "controller_id": "con2",
                    "port_id": 2,
                    "offset": -0.08838355989583335,
                    "__class__": "quam.components.ports.analog_inputs.OPXPlusAnalogInputPort"
                }
            }
        }
    },
    "__class__": "quam_libs.components.quam_root.OPXPlusQuAM"
}