{
  "authors_count": 13,
  "by_repository": {
    "android-app": {
      "authors_count": 1,
      "cycle_time_p50": 602.443,
      "cycle_time_p90": 1003.875,
      "pr_count": 2,
      "reviewers_count": 1
    },
    "auth-service": {
      "authors_count": 1,
      "cycle_time_p50": 369.834,
      "cycle_time_p90": 3372.781,
      "pr_count": 6,
      "reviewers_count": 2
    },
    "ci-scripts": {
      "authors_count": 1,
      "cycle_time_p50": 252.741,
      "cycle_time_p90": 252.741,
      "pr_count": 1,
      "reviewers_count": 1
    },
    "dashboard-api": {
      "authors_count": 1,
      "cycle_time_p50": 476.552,
      "cycle_time_p90": 476.552,
      "pr_count": 1,
      "reviewers_count": 1
    },
    "data-warehouse": {
      "authors_count": 1,
      "cycle_time_p50": 891.138,
      "cycle_time_p90": 1754.575,
      "pr_count": 3,
      "reviewers_count": 1
    },
    "design-system": {
      "authors_count": 1,
      "cycle_time_p50": 113.916,
      "cycle_time_p90": 113.916,
      "pr_count": 1,
      "reviewers_count": 1
    },
    "etl-jobs": {
      "authors_count": 1,
      "cycle_time_p50": 184.271,
      "cycle_time_p90": 1978.128,
      "pr_count": 3,
      "reviewers_count": 1
    },
    "feature-store": {
      "authors_count": 1,
      "cycle_time_p50": 6904.006,
      "cycle_time_p90": 6904.006,
      "pr_count": 1,
      "reviewers_count": 1
    },
    "forms-lib": {
      "authors_count": 1,
      "cycle_time_p50": 580.424,
      "cycle_time_p90": 580.424,
      "pr_count": 1,
      "reviewers_count": 1
    },
    "gateway-core": {
      "authors_count": 1,
      "cycle_time_p50": 572.672,
      "cycle_time_p90": 911.06,
      "pr_count": 2,
      "reviewers_count": 1
    },
    "inference-service": {
      "authors_count": 1,
      "cycle_time_p50": 367.038,
      "cycle_time_p90": 367.038,
      "pr_count": 1,
      "reviewers_count": 1
    },
    "ios-app": {
      "authors_count": 1,
      "cycle_time_p50": 366.451,
      "cycle_time_p90": 866.413,
      "pr_count": 4,
      "reviewers_count": 1
    },
    "metrics-collector": {
      "authors_count": 1,
      "cycle_time_p50": 316.93,
      "cycle_time_p90": 316.93,
      "pr_count": 1,
      "reviewers_count": 1
    },
    "model-training": {
      "authors_count": 1,
      "cycle_time_p50": 513.405,
      "cycle_time_p90": 513.405,
      "pr_count": 1,
      "reviewers_count": 1
    },
    "monitoring-stack": {
      "authors_count": 1,
      "cycle_time_p50": 346.126,
      "cycle_time_p90": 494.554,
      "pr_count": 3,
      "reviewers_count": 1
    },
    "notification-service": {
      "authors_count": 1,
      "cycle_time_p50": 237.37,
      "cycle_time_p90": 4429.641,
      "pr_count": 4,
      "reviewers_count": 1
    },
    "rate-limiter": {
      "authors_count": 1,
      "cycle_time_p50": 71.677,
      "cycle_time_p90": 71.677,
      "pr_count": 1,
      "reviewers_count": 1
    },
    "react-shell": {
      "authors_count": 1,
      "cycle_time_p50": 100.988,
      "cycle_time_p90": 100.988,
      "pr_count": 1,
      "reviewers_count": 1
    },
    "report-generator": {
      "authors_count": 1,
      "cycle_time_p50": 1.806,
      "cycle_time_p90": 1.806,
      "pr_count": 1,
      "reviewers_count": 1
    },
    "shared-core": {
      "authors_count": 1,
      "cycle_time_p50": 460.764,
      "cycle_time_p90": 464.447,
      "pr_count": 2,
      "reviewers_count": 1
    },
    "stream-processor": {
      "authors_count": 1,
      "cycle_time_p50": 1124.657,
      "cycle_time_p90": 1993.998,
      "pr_count": 2,
      "reviewers_count": 1
    },
    "terraform-modules": {
      "authors_count": 1,
      "cycle_time_p50": 487.614,
      "cycle_time_p90": 487.614,
      "pr_count": 1,
      "reviewers_count": 1
    },
    "user-service": {
      "authors_count": 1,
      "cycle_time_p50": 614.843,
      "cycle_time_p90": 614.843,
      "pr_count": 1,
      "reviewers_count": 1
    }
  },
  "cycle_time_p50": 211.092,
  "cycle_time_p90": 1475.921,
  "end_date": "2021-06-27",
  "pr_count": 44,
  "reviewers_count": 19,
  "start_date": "2021-06-21",
  "week": "2021-W25"
}
