{
  "authors_count": 14,
  "by_repository": {
    "android-app": {
      "authors_count": 1,
      "cycle_time_p50": 430.214,
      "cycle_time_p90": 1014.758,
      "pr_count": 4,
      "reviewers_count": 1
    },
    "auth-service": {
      "authors_count": 1,
      "cycle_time_p50": 296.353,
      "cycle_time_p90": 712.891,
      "pr_count": 5,
      "reviewers_count": 2
    },
    "ci-scripts": {
      "authors_count": 1,
      "cycle_time_p50": 372.435,
      "cycle_time_p90": 372.435,
      "pr_count": 1,
      "reviewers_count": 1
    },
    "dashboard-api": {
      "authors_count": 1,
      "cycle_time_p50": 251.511,
      "cycle_time_p90": 251.511,
      "pr_count": 1,
      "reviewers_count": 1
    },
    "data-warehouse": {
      "authors_count": 1,
      "cycle_time_p50": 894.822,
      "cycle_time_p90": 894.822,
      "pr_count": 1,
      "reviewers_count": 1
    },
    "design-system": {
      "authors_count": 1,
      "cycle_time_p50": 2037.697,
      "cycle_time_p90": 3562.488,
      "pr_count": 2,
      "reviewers_count": 1
    },
    "etl-jobs": {
      "authors_count": 1,
      "cycle_time_p50": 249.279,
      "cycle_time_p90": 249.279,
      "pr_count": 1,
      "reviewers_count": 1
    },
    "feature-store": {
      "authors_count": 1,
      "cycle_time_p50": 197.641,
      "cycle_time_p90": 197.641,
      "pr_count": 1,
      "reviewers_count": 1
    },
    "forms-lib": {
      "authors_count": 1,
      "cycle_time_p50": 114.46,
      "cycle_time_p90": 114.46,
      "pr_count": 1,
      "reviewers_count": 1
    },
    "gateway-core": {
      "authors_count": 1,
      "cycle_time_p50": 10.419,
      "cycle_time_p90": 10.419,
      "pr_count": 1,
      "reviewers_count": 1
    },
    "inference-service": {
      "authors_count": 1,
      "cycle_time_p50": 315.287,
      "cycle_time_p90": 315.287,
      "pr_count": 1,
      "reviewers_count": 1
    },
    "ios-app": {
      "authors_count": 1,
      "cycle_time_p50": 1007.368,
      "cycle_time_p90": 1007.368,
      "pr_count": 1,
      "reviewers_count": 1
    },
    "metrics-collector": {
      "authors_count": 1,
      "cycle_time_p50": 1817.847,
      "cycle_time_p90": 1817.847,
      "pr_count": 1,
      "reviewers_count": 1
    },
    "model-training": {
      "authors_count": 1,
      "cycle_time_p50": 3749.334,
      "cycle_time_p90": 3749.334,
      "pr_count": 1,
      "reviewers_count": 1
    },
    "monitoring-stack": {
      "authors_count": 1,
      "cycle_time_p50": 352.615,
      "cycle_time_p90": 5042.913,
      "pr_count": 3,
      "reviewers_count": 1
    },
    "notification-service": {
      "authors_count": 1,
      "cycle_time_p50": 648.776,
      "cycle_time_p90": 4717.085,
      "pr_count": 6,
      "reviewers_count": 2
    },
    "rate-limiter": {
      "authors_count": 1,
      "cycle_time_p50": 968.75,
      "cycle_time_p90": 968.75,
      "pr_count": 1,
      "reviewers_count": 1
    },
    "react-shell": {
      "authors_count": 1,
      "cycle_time_p50": 1494.414,
      "cycle_time_p90": 1494.414,
      "pr_count": 1,
      "reviewers_count": 1
    },
    "report-generator": {
      "authors_count": 1,
      "cycle_time_p50": 49.647,
      "cycle_time_p90": 49.647,
      "pr_count": 1,
      "reviewers_count": 1
    },
    "shared-core": {
      "authors_count": 1,
      "cycle_time_p50": 9887.282,
      "cycle_time_p90": 9887.282,
      "pr_count": 1,
      "reviewers_count": 1
    },
    "stream-processor": {
      "authors_count": 1,
      "cycle_time_p50": 998.837,
      "cycle_time_p90": 1385.633,
      "pr_count": 2,
      "reviewers_count": 1
    },
    "terraform-modules": {
      "authors_count": 1,
      "cycle_time_p50": 66.355,
      "cycle_time_p90": 66.355,
      "pr_count": 1,
      "reviewers_count": 1
    },
    "user-service": {
      "authors_count": 3,
      "cycle_time_p50": 271.579,
      "cycle_time_p90": 1618.301,
      "pr_count": 11,
      "reviewers_count": 4
    }
  },
  "cycle_time_p50": 515.42,
  "cycle_time_p90": 5689.497,
  "end_date": "2021-06-20",
  "pr_count": 49,
  "reviewers_count": 22,
  "start_date": "2021-06-14",
  "week": "2021-W24"
}
