<?xml version="1.0"?>
<Annotation createdAt="1999-04-01" createdBy="graebe" id="BIB.Czapor_89a">
<!-- $Id: BIB.Czapor_89a.xml,v 1.1 2006/03/05 13:44:06 graebe Exp $ -->
  <note>The paper [BIB/Czapor_89a] discusses the following examples:

Trinks as Problem 1
Katsura_5 as Problem 2
Rose as Problem 3
</note>
  <relatesTo>
    <OWL xref="Trinks" class="Ideal"/>
    <OWL xref="Katsura_5" class="Ideal"/>
    <OWL xref="Rose" class="Ideal"/>
    <OWL xref="Czapor_89a" class="BIB"/>
  </relatesTo>
  <Comment/>
  <ChangeLog/>
</Annotation>
