<?xml version="1.0"?>
<Annotation createdAt="1999-11-01" createdBy="witte" id="Geometry.Chou.240">
<!-- $Id: Geometry.Chou.240.xml,v 1.1 2006/03/04 21:19:08 graebe Exp $ -->
  <note>
If $A$, $B$, $C$ are the centers of three equal circles $(A)$, $(B)$, $(C)$
having a point $L$ in common, and $D$, $E$, $F$ are the other points which
the circles $(B)$ and $(C)$, $(C)$ and $(A)$, $(A)$ and $(B)$ have in
common, show that the circle $DEF$ is equal to the given circles, and that
the center of this circle coincides with the orthocenter of the triangle
$ABC$.

\begin{keywords}
geometry theorem proving
\end{keywords}
</note>
  <relatesTo/><Comment>Submitted by Malte Witte</Comment>
  <ChangeLog>
    <changed at="2006-03-04" by="graebe">compiled from XMLData PROBLEMS/Geometry/Chou/240</changed>
  </ChangeLog>
</Annotation>
