<?xml version="1.0"?>
<Annotation createdAt="1999-11-01" createdBy="witte" id="Geometry.Chou.310">
<!-- $Id: Geometry.Chou.310.xml,v 1.1 2006/03/04 21:19:08 graebe Exp $ -->
  <note>
The four Simson lines of a point of a circle for the four triangles
determined by the vertices of a quadrilateral inscribed in that circle,
admit the point considered for their Miquel point.

\begin{keywords}
geometry theorem proving
\end{keywords}
</note>
  <relatesTo/><Comment>Submitted by Malte Witte</Comment>
  <ChangeLog>
    <changed at="2006-03-04" by="graebe">compiled from XMLData PROBLEMS/Geometry/Chou/310</changed>
  </ChangeLog>
</Annotation>
