<?xml version="1.0"?>
<Annotation createdAt="1999-11-01" createdBy="witte" id="Geometry.Chou.402">
<!-- $Id: Geometry.Chou.402.xml,v 1.1 2006/03/04 21:19:08 graebe Exp $ -->
  <note>
Show that an altitude of a triangle is the radical axis of the two circles
having for diameters the medians issued from the other two vertices.

\begin{keywords}
geometry theorem proving
\end{keywords}
</note>
  <relatesTo/><Comment>Submitted by Malte Witte</Comment>
  <ChangeLog>
    <changed at="2006-03-04" by="graebe">compiled from XMLData PROBLEMS/Geometry/Chou/402</changed>
  </ChangeLog>
</Annotation>
