<?xml version="1.0"?>
<INTPSAnnotation createdAt="2000-03-22" createdBy="graebe" id="Geometry.Thebault_1">
<!-- $Id: Geometry.Thebault_1.xml,v 1.2 2006/03/05 11:32:56 graebe Exp $ -->
  <theDegreeList>2 2 2 2 4 4</theDegreeList>
  <theLengthsList>6 6 6 6 9 9</theLengthsList>
  <thePolynomialSystem>
    <XML XMLType="IntegerPolynomialSystem" url="sdxml:INTPS/Geometry.Thebault_1.xml"/>
  </thePolynomialSystem>
  <Comment/>
  <ChangeLog>
    <changed at="2006-03-03" by="graebe">compiled from XMLData INTPS/Geometry/Thebault_1</changed>
    <changed at="2006-03-03" by="graebe">TODO:theDegreeList and theLengthsList have to be fixed</changed>
  </ChangeLog>
</INTPSAnnotation>
